python_thenounproject-1.0.1a1.dist-info/DESCRIPTION.rst
python_thenounproject-1.0.1a1.dist-info/METADATA
python_thenounproject-1.0.1a1.dist-info/RECORD
python_thenounproject-1.0.1a1.dist-info/WHEEL
python_thenounproject-1.0.1a1.dist-info/metadata.json
python_thenounproject-1.0.1a1.dist-info/top_level.txt
python_thenounproject-1.0.1a1.dist-info/zip-safe
thenounproject/__init__.py
thenounproject/api.py
thenounproject/client.py
thenounproject/collection.py
thenounproject/enterprise.py
thenounproject/expections.py
thenounproject/icon.py
thenounproject/models.py
thenounproject/usage.py
thenounproject/user.py
