Metadata-Version: 2.0
Name: python-thenounproject
Version: 1.0.1a1
Summary: A Python client for the TheNounProject API.
Home-page: http://github.com/yakupadakli/python-thenounproject.git
Author: Yakup Adaklı
Author-email: yakup.adakli@gmail.com
License: MIT
Keywords: the noun project library
Platform: UNKNOWN
Classifier: Development Status :: 3 - Alpha
Classifier: Topic :: Software Development :: Libraries
Classifier: License :: OSI Approved :: MIT License
Classifier: Operating System :: OS Independent
Classifier: Programming Language :: Python :: 2.7
Classifier: Programming Language :: Python :: 3.3
Classifier: Programming Language :: Python :: 3.4
Classifier: Programming Language :: Python :: 3.6
Requires-Dist: requests (==2.18.4)
Requires-Dist: requests-oauthlib (==0.8.0)
Requires-Dist: six (==1.10.0)
